Metadata-Version: 1.0
Name: nginx2f5
Version: 1.0
Summary: This is a Python script to convert nginx configuration to F5 syntax
Home-page: https://pypi.python.org/pypi?:action=display&name=nginx2f5&version=1.0
Author: Pete White
Author-email: pwhite@f5.com
License: PSF
Platform: UNKNOWN
